{
  "schemaVersion": "0.1",
  "generatedAt": "2026-06-19T16:31:38.210Z",
  "projectId": "atomic-skills",
  "plan": {
    "slug": "deadline-burnup-forecast",
    "title": "Deadline Burn-up Forecast (Earned Value / SPI)",
    "status": "active"
  },
  "phase": {
    "id": "F3",
    "slug": "deadline-burnup-forecast-f3-serie-earned-vs-planned-deadline-wi",
    "title": "Série earned-vs-planned + deadline + wiring de recompute",
    "index": 4,
    "total": 6,
    "status": "active"
  },
  "tasks": {
    "done": 2,
    "total": 3,
    "blocked": 0
  },
  "gates": {
    "met": 0,
    "total": 1
  },
  "nextAction": "Dispatch Codex (Mode 2) para T-002 (buildSeries: burnup.json + spi.json) em novo worktree; work-order DEVE carregar L-001 (Number.isFinite nos escalares emit: plannedValue/earnedCount/earnedProxy/spiProxy/spiCount) + L-003 (teste em tests/ plural); merge-back serial; re-verificar no primary: node --test tests/emit-series.test.js && node --test tests/schema-drift.test.js",
  "flags": {
    "drift": false,
    "multipleActivePlans": false
  },
  "sources": [
    {
      "path": ".atomic-skills/projects/atomic-skills/deadline-burnup-forecast/plan.md",
      "lastUpdated": "2026-06-19T09:20:00Z"
    },
    {
      "path": ".atomic-skills/projects/atomic-skills/deadline-burnup-forecast/phases/f3-serie-earned-vs-planned-deadline-wi.md",
      "lastUpdated": "2026-06-19T15:32:42Z"
    }
  ]
}
