{
  "schemaVersion": "0.1",
  "generatedAt": "2026-06-19T12:12:05.271Z",
  "projectId": "atomic-skills",
  "plan": {
    "slug": "deadline-burnup-forecast",
    "title": "Deadline Burn-up Forecast (Earned Value / SPI)",
    "status": "active"
  },
  "phase": {
    "id": "F2",
    "slug": "deadline-burnup-forecast-f2-peso-por-task-proxy-estrutural-roll",
    "title": "Peso por task: proxy estrutural + rollups",
    "index": 3,
    "total": 6,
    "status": "active"
  },
  "tasks": {
    "done": 1,
    "total": 3,
    "blocked": 0
  },
  "gates": {
    "met": 0,
    "total": 1
  },
  "nextAction": "Start T-001: — Campo weight no schema da task + rebuild do bundle",
  "flags": {
    "drift": false,
    "multipleActivePlans": false
  },
  "sources": [
    {
      "path": ".atomic-skills/projects/atomic-skills/deadline-burnup-forecast/plan.md",
      "lastUpdated": "2026-06-19T09:20:00Z"
    },
    {
      "path": ".atomic-skills/projects/atomic-skills/deadline-burnup-forecast/phases/f2-peso-por-task-proxy-estrutural-roll.md",
      "lastUpdated": "2026-06-19T11:20:50Z"
    }
  ]
}
